odoo/addons/web_pivot_computed_measure/README.rst
odoo/addons/web_pivot_computed_measure/__init__.py
odoo/addons/web_pivot_computed_measure/__manifest__.py
odoo/addons/web_pivot_computed_measure/i18n/es.po
odoo/addons/web_pivot_computed_measure/i18n/web_pivot_computed_measure.pot
odoo/addons/web_pivot_computed_measure/readme/CONTRIBUTORS.rst
odoo/addons/web_pivot_computed_measure/readme/DESCRIPTION.rst
odoo/addons/web_pivot_computed_measure/readme/ROADMAP.rst
odoo/addons/web_pivot_computed_measure/readme/USAGE.rst
odoo/addons/web_pivot_computed_measure/static/description/icon.png
odoo/addons/web_pivot_computed_measure/static/description/index.html
odoo/addons/web_pivot_computed_measure/static/src/js/pivot_controller.js
odoo/addons/web_pivot_computed_measure/static/src/js/pivot_model.js
odoo/addons/web_pivot_computed_measure/static/src/xml/web_pivot_computed_measure.xml
odoo/addons/web_pivot_computed_measure/view/assets.xml
odoo12_addon_web_pivot_computed_measure-12.0.1.0.3.dist-info/METADATA
odoo12_addon_web_pivot_computed_measure-12.0.1.0.3.dist-info/WHEEL
odoo12_addon_web_pivot_computed_measure-12.0.1.0.3.dist-info/top_level.txt
odoo12_addon_web_pivot_computed_measure-12.0.1.0.3.dist-info/RECORD
